sqlalchemy_querytools/__init__.py
sqlalchemy_querytools/_internal.py
sqlalchemy_querytools/pagination.py
sqlalchemy_querytools/search.py
sqlalchemy_querytools/sort.py
sqlalchemy_querytools/types.py
sqlalchemy_querytools-0.1.2.dist-info/licenses/LICENSE
sqlalchemy_querytools-0.1.2.dist-info/METADATA
sqlalchemy_querytools-0.1.2.dist-info/WHEEL
sqlalchemy_querytools-0.1.2.dist-info/RECORD
