Metadata-Version: 2.4
Name: sqlalchemy-querytools
Version: 0.1.2
Summary: Helpers for searching, sorting and pagination for SQLAlchemy SELECT queries
License: MIT
License-File: LICENSE
Author: Vadim Andronik
Author-email: andronnikovvv@gmail.com
Requires-Python: >=3.9,<4.0
Classifier: License :: OSI Approved :: MIT License
Classifier: Programming Language :: Python :: 3
Classifier: Programming Language :: Python :: 3.9
Classifier: Programming Language :: Python :: 3.10
Classifier: Programming Language :: Python :: 3.11
Classifier: Programming Language :: Python :: 3.12
Classifier: Programming Language :: Python :: 3.13
Classifier: Programming Language :: Python :: 3.14
Requires-Dist: SQLAlchemy (>=1.4,<2.2)
Requires-Dist: typing-extensions (>=4.0,<5.0)
Project-URL: Repository, https://github.com/ronik-v/sqlalchemy-querytools
